test_update_firewall_ip.py
update_firewall_ip.py
gcpfwup-1.0.1.dist-info/LICENSE
gcpfwup-1.0.1.dist-info/METADATA
gcpfwup-1.0.1.dist-info/WHEEL
gcpfwup-1.0.1.dist-info/entry_points.txt
gcpfwup-1.0.1.dist-info/top_level.txt
gcpfwup-1.0.1.dist-info/RECORD
