Metadata-Version: 2.1
Name: gcpfwup
Version: 1.0.1
Summary: Firewall rule updater for Google Cloud Platform
Home-page: https://github.com/peterdemin/gcpfwup
Author: Peter Demin
Author-email: peterdemin@gmail.com
License: MIT license
Keywords: GCP Firewall
Classifier: Development Status :: 5 - Production/Stable
Classifier: Intended Audience :: Developers
Classifier: License :: OSI Approved :: MIT License
Classifier: Natural Language :: English
Classifier: Programming Language :: Python :: 3
Requires-Python: >=3.8
License-File: LICENSE
Requires-Dist: google-cloud-compute
Requires-Dist: urllib3
